brogscursor/__init__.py
brogscursor/cli.py
brogscursor/recorder.py
brogscursor/utils.py
brogscursor-0.1.0.dist-info/licenses/LICENSE
brogscursor-0.1.0.dist-info/METADATA
brogscursor-0.1.0.dist-info/WHEEL
brogscursor-0.1.0.dist-info/entry_points.txt
brogscursor-0.1.0.dist-info/top_level.txt
brogscursor-0.1.0.dist-info/RECORD
