Metadata-Version: 2.4
Name: brogscursor
Version: 0.1.0
Summary: Precise mouse and keyboard action recorder and replayer
Home-page: https://github.com/yourusername/brogscursor
Author: Your Name
Author-email: Your Name <your.email@example.com>
Maintainer-email: Your Name <your.email@example.com>
License: MIT
Project-URL: Homepage, https://github.com/yourusername/brogscursor
Project-URL: Issues, https://github.com/yourusername/brogscursor/issues
Project-URL: Documentation, https://github.com/yourusername/brogscursor#readme
Keywords: mouse,keyboard,record,replay,automation
Classifier: Programming Language :: Python :: 3
Classifier: License :: OSI Approved :: MIT License
Classifier: Operating System :: OS Independent
Classifier: Topic :: Utilities
Requires-Python: >=3.6
License-File: LICENSE
Requires-Dist: pyautogui>=0.9.53
Requires-Dist: pynput>=1.7.6
Requires-Dist: rich>=12.5.0
Dynamic: author
Dynamic: home-page
Dynamic: license-file
Dynamic: requires-python
